djpb/__init__.py
djpb/custom_field.py
djpb/django_to_proto.py
djpb/gen_proto.py
djpb/proto_to_django.py
djpb/registry.py
djpb/serializers.py
djpb/signals.py
djpb/stubs.py
djpb/util.py
djpb/drf/__init__.py
djpb/drf/parsers.py
djpb/drf/renderers.py
djpb/drf/serializers.py
djpb/management/__init__.py
djpb/management/commands/__init__.py
djpb/management/commands/gen_proto.py
djpb-0.19.0.dist-info/METADATA
djpb-0.19.0.dist-info/WHEEL
djpb-0.19.0.dist-info/top_level.txt
djpb-0.19.0.dist-info/RECORD
