Metadata-Version: 2.1
Name: djpb
Version: 0.19.0
Summary: UNKNOWN
Home-page: https://github.com/scientifichackers/djpb
Author: Dev Aggarwal,
Author-email: devxpy@gmail.com
License: UNKNOWN
Platform: UNKNOWN
Requires-Python: >=3.8.0
Requires-Dist: django (>=3.1)
Requires-Dist: protobuf
Provides-Extra: dev
Requires-Dist: twine ; extra == 'dev'
Provides-Extra: drf
Requires-Dist: djangorestframework ; extra == 'drf'
Requires-Dist: msgpack ; extra == 'drf'
